<?xml version="1.0" encoding="utf-8"?>
<Data>
    <!-- Processing Recipes -->
    <Recipe>
        <Id>plank_recipe</Id>
        <category>materials</category>
        <result>plank</result>
        <timeCraft>2</timeCraft>
        <components>
            <li>
                <Options>
                    <li>
                        <thingId>wood</thingId>
                        <quantity>1</quantity>
                    </li>
                </Options>
            </li>
        </components>
        <qualities>
            <li>
                <id>tool_axe</id>
                <level>1</level>
            </li>
        </qualities>
    </Recipe>
    
    <Recipe>
        <Id>stick_recipe</Id>
        <category>materials</category>
        <result>stick</result>
        <timeCraft>1</timeCraft>
        <components>
            <li>
                <Options>
                    <li>
                        <thingId>wood</thingId>
                        <quantity>1</quantity>
                    </li>
                </Options>
            </li>
        </components>
        <qualities>
            <li>
                <id>tool_cut</id>
                <level>1</level>
            </li>
        </qualities>
    </Recipe>
    
    <Recipe>
        <Id>rope_recipe</Id>
        <category>materials</category>
        <result>rope</result>
        <timeCraft>3</timeCraft>
        <components>
            <li>
                <Options>
                    <li>
                        <thingId>fiber</thingId>
                        <quantity>5</quantity>
                    </li>
                </Options>
            </li>
        </components>
        <qualities>
            <li>
                <id>tool_crafting</id>
                <level>1</level>
            </li>
        </qualities>
    </Recipe>
    
    <Recipe>
        <Id>cloth_recipe</Id>
        <category>materials</category>
        <result>cloth</result>
        <timeCraft>4</timeCraft>
        <components>
            <li>
                <Options>
                    <li>
                        <thingId>fiber</thingId>
                        <quantity>4</quantity>
                    </li>
                </Options>
            </li>
        </components>
        <qualities>
            <li>
                <id>tool_crafting</id>
                <level>1</level>
            </li>
        </qualities>
    </Recipe>
    
    <Recipe>
        <Id>charcoal_recipe</Id>
        <category>materials</category>
        <result>charcoal</result>
        <timeCraft>5</timeCraft>
        <components>
            <li>
                <Options>
                    <li>
                        <thingId>wood</thingId>
                        <quantity>2</quantity>
                    </li>
                </Options>
            </li>
        </components>
        <qualities>
            <li>
                <id>tool_hammer</id>
                <level>1</level>
            </li>
        </qualities>
    </Recipe>
    
    <Recipe>
        <Id>leather_recipe</Id>
        <category>materials</category>
        <result>leather</result>
        <timeCraft>6</timeCraft>
        <components>
            <li>
                <Options>
                    <li>
                        <thingId>raw_hide</thingId>
                        <quantity>1</quantity>
                    </li>
                </Options>
            </li>
        </components>
        <qualities>
            <li>
                <id>tool_cut</id>
                <level>1</level>
            </li>
        </qualities>
    </Recipe>
    
    <Recipe>
        <Id>brick_recipe</Id>
        <category>materials</category>
        <result>brick</result>
        <timeCraft>4</timeCraft>
        <components>
            <li>
                <Options>
                    <li>
                        <thingId>clay</thingId>
                        <quantity>2</quantity>
                    </li>
                </Options>
            </li>
        </components>
        <qualities>
            <li>
                <id>tool_hammer</id>
                <level>1</level>
            </li>
        </qualities>
    </Recipe>
    
    <Recipe>
        <Id>glass_recipe</Id>
        <category>materials</category>
        <result>glass</result>
        <timeCraft>5</timeCraft>
        <components>
            <li>
                <Options>
                    <li>
                        <thingId>sand</thingId>
                        <quantity>3</quantity>
                    </li>
                </Options>
            </li>
        </components>
        <qualities>
            <li>
                <id>tool_hammer</id>
                <level>1</level>
            </li>
        </qualities>
    </Recipe>
    
    <Recipe>
        <Id>nails_recipe</Id>
        <category>materials</category>
        <result>nails</result>
        <timeCraft>2</timeCraft>
        <components>
            <li>
                <Options>
                    <li>
                        <thingId>iron_ingot</thingId>
                        <quantity>1</quantity>
                    </li>
                </Options>
            </li>
        </components>
        <qualities>
            <li>
                <id>tool_hammer</id>
                <level>2</level>
            </li>
        </qualities>
    </Recipe>
    
    <Recipe>
        <Id>handle_recipe</Id>
        <category>materials</category>
        <result>handle</result>
        <timeCraft>1</timeCraft>
        <components>
            <li>
                <Options>
                    <li>
                        <thingId>stick</thingId>
                        <quantity>1</quantity>
                    </li>
                </Options>
            </li>
            <li>
                <Options>
                    <li>
                        <thingId>rope</thingId>
                        <quantity>1</quantity>
                    </li>
                </Options>
            </li>
        </components>
        <qualities>
            <li>
                <id>tool_crafting</id>
                <level>1</level>
            </li>
        </qualities>
    </Recipe>
    
    <!-- Smelting Recipes -->
    <Recipe>
        <Id>iron_ingot_recipe</Id>
        <category>smelting</category>
        <result>iron_ingot</result>
        <timeCraft>8</timeCraft>
        <components>
            <li>
                <Options>
                    <li>
                        <thingId>iron_ore</thingId>
                        <quantity>2</quantity>
                    </li>
                </Options>
            </li>
            <li>
                <Options>
                    <li>
                        <thingId>coal</thingId>
                        <quantity>1</quantity>
                    </li>
                </Options>
            </li>
        </components>
        <qualities>
            <li>
                <id>tool_hammer</id>
                <level>2</level>
            </li>
        </qualities>
    </Recipe>
    
    <Recipe>
        <Id>copper_ingot_recipe</Id>
        <category>smelting</category>
        <result>copper_ingot</result>
        <timeCraft>6</timeCraft>
        <components>
            <li>
                <Options>
                    <li>
                        <thingId>copper_ore</thingId>
                        <quantity>2</quantity>
                    </li>
                </Options>
            </li>
            <li>
                <Options>
                    <li>
                        <thingId>coal</thingId>
                        <quantity>1</quantity>
                    </li>
                </Options>
            </li>
        </components>
        <qualities>
            <li>
                <id>tool_hammer</id>
                <level>1</level>
            </li>
        </qualities>
    </Recipe>
    
    <Recipe>
        <Id>gold_ingot_recipe</Id>
        <category>smelting</category>
        <result>gold_ingot</result>
        <timeCraft>10</timeCraft>
        <components>
            <li>
                <Options>
                    <li>
                        <thingId>gold_ore</thingId>
                        <quantity>3</quantity>
                    </li>
                </Options>
            </li>
            <li>
                <Options>
                    <li>
                        <thingId>coal</thingId>
                        <quantity>2</quantity>
                    </li>
                </Options>
            </li>
        </components>
        <qualities>
            <li>
                <id>tool_hammer</id>
                <level>3</level>
            </li>
        </qualities>
    </Recipe>
    
    <Recipe>
        <Id>iron_rod_recipe</Id>
        <category>smelting</category>
        <result>iron_rod</result>
        <timeCraft>4</timeCraft>
        <components>
            <li>
                <Options>
                    <li>
                        <thingId>iron_ingot</thingId>
                        <quantity>1</quantity>
                    </li>
                </Options>
            </li>
        </components>
        <qualities>
            <li>
                <id>tool_hammer</id>
                <level>2</level>
            </li>
        </qualities>
    </Recipe>
    
    <Recipe>
        <Id>iron_arrow_recipe</Id>
        <category>ammunition</category>
        <result>iron_arrow</result>
        <timeCraft>2</timeCraft>
        <components>
            <li>
                <Options>
                    <li>
                        <thingId>stick</thingId>
                        <quantity>1</quantity>
                    </li>
                </Options>
            </li>
            <li>
                <Options>
                    <li>
                        <thingId>iron_ingot</thingId>
                        <quantity>1</quantity>
                    </li>
                </Options>
            </li>
            <li>
                <Options>
                    <li>
                        <thingId>feather</thingId>
                        <quantity>1</quantity>
                    </li>
                </Options>
            </li>
        </components>
        <qualities>
            <li>
                <id>tool_cut</id>
                <level>1</level>
            </li>
        </qualities>
    </Recipe>
    
    <!-- Tool Recipes -->
    <Recipe>
        <Id>stone_axe_recipe</Id>
        <category>tools</category>
        <result>stone_axe</result>
        <timeCraft>4</timeCraft>
        <components>
            <li>
                <Options>
                    <li>
                        <thingId>stone</thingId>
                        <quantity>2</quantity>
                    </li>
                </Options>
            </li>
            <li>
                <Options>
                    <li>
                        <thingId>stick</thingId>
                        <quantity>1</quantity>
                    </li>
                </Options>
            </li>
            <li>
                <Options>
                    <li>
                        <thingId>rope</thingId>
                        <quantity>1</quantity>
                    </li>
                </Options>
            </li>
        </components>
        <qualities>
            <li>
                <id>tool_crafting</id>
                <level>1</level>
            </li>
        </qualities>
    </Recipe>
    
    <Recipe>
        <Id>stone_pickaxe_recipe</Id>
        <category>tools</category>
        <result>stone_pickaxe</result>
        <timeCraft>4</timeCraft>
        <components>
            <li>
                <Options>
                    <li>
                        <thingId>stone</thingId>
                        <quantity>3</quantity>
                    </li>
                </Options>
            </li>
            <li>
                <Options>
                    <li>
                        <thingId>stick</thingId>
                        <quantity>1</quantity>
                    </li>
                </Options>
            </li>
            <li>
                <Options>
                    <li>
                        <thingId>rope</thingId>
                        <quantity>1</quantity>
                    </li>
                </Options>
            </li>
        </components>
        <qualities>
            <li>
                <id>tool_crafting</id>
                <level>1</level>
            </li>
        </qualities>
    </Recipe>
    
    <Recipe>
        <Id>iron_axe_recipe</Id>
        <category>tools</category>
        <result>iron_axe</result>
        <timeCraft>6</timeCraft>
        <components>
            <li>
                <Options>
                    <li>
                        <thingId>iron_ingot</thingId>
                        <quantity>2</quantity>
                    </li>
                </Options>
            </li>
            <li>
                <Options>
                    <li>
                        <thingId>stick</thingId>
                        <quantity>1</quantity>
                    </li>
                </Options>
            </li>
            <li>
                <Options>
                    <li>
                        <thingId>rope</thingId>
                        <quantity>1</quantity>
                    </li>
                </Options>
            </li>
        </components>
        <qualities>
            <li>
                <id>tool_hammer</id>
                <level>2</level>
            </li>
        </qualities>
    </Recipe>
    
    <Recipe>
        <Id>iron_pickaxe_recipe</Id>
        <category>tools</category>
        <result>iron_pickaxe</result>
        <timeCraft>6</timeCraft>
        <components>
            <li>
                <Options>
                    <li>
                        <thingId>iron_ingot</thingId>
                        <quantity>3</quantity>
                    </li>
                </Options>
            </li>
            <li>
                <Options>
                    <li>
                        <thingId>stick</thingId>
                        <quantity>1</quantity>
                    </li>
                </Options>
            </li>
            <li>
                <Options>
                    <li>
                        <thingId>rope</thingId>
                        <quantity>1</quantity>
                    </li>
                </Options>
            </li>
        </components>
        <qualities>
            <li>
                <id>tool_hammer</id>
                <level>2</level>
            </li>
        </qualities>
    </Recipe>
    
    <Recipe>
        <Id>wooden_bow_recipe</Id>
        <category>weapons</category>
        <result>wooden_bow</result>
        <timeCraft>5</timeCraft>
        <components>
            <li>
                <Options>
                    <li>
                        <thingId>stick</thingId>
                        <quantity>3</quantity>
                    </li>
                </Options>
            </li>
            <li>
                <Options>
                    <li>
                        <thingId>rope</thingId>
                        <quantity>2</quantity>
                    </li>
                </Options>
            </li>
        </components>
        <qualities>
            <li>
                <id>tool_crafting</id>
                <level>1</level>
            </li>
        </qualities>
    </Recipe>
    
    <Recipe>
        <Id>iron_sword_recipe</Id>
        <category>weapons</category>
        <result>iron_sword</result>
        <timeCraft>8</timeCraft>
        <components>
            <li>
                <Options>
                    <li>
                        <thingId>iron_ingot</thingId>
                        <quantity>3</quantity>
                    </li>
                </Options>
            </li>
            <li>
                <Options>
                    <li>
                        <thingId>stick</thingId>
                        <quantity>1</quantity>
                    </li>
                </Options>
            </li>
            <li>
                <Options>
                    <li>
                        <thingId>leather</thingId>
                        <quantity>1</quantity>
                    </li>
                </Options>
            </li>
        </components>
        <qualities>
            <li>
                <id>tool_hammer</id>
                <level>3</level>
            </li>
        </qualities>
    </Recipe>
    
    <Recipe>
        <Id>leather_armor_recipe</Id>
        <category>armor</category>
        <result>leather_chestplate</result>
        <timeCraft>10</timeCraft>
        <components>
            <li>
                <Options>
                    <li>
                        <thingId>leather</thingId>
                        <quantity>4</quantity>
                    </li>
                </Options>
            </li>
            <li>
                <Options>
                    <li>
                        <thingId>thread</thingId>
                        <quantity>2</quantity>
                    </li>
                </Options>
            </li>
        </components>
        <qualities>
            <li>
                <id>tool_crafting</id>
                <level>2</level>
            </li>
        </qualities>
    </Recipe>
    
    <Recipe>
        <Id>iron_chestplate_recipe</Id>
        <category>armor</category>
        <result>iron_chestplate</result>
        <timeCraft>15</timeCraft>
        <components>
            <li>
                <Options>
                    <li>
                        <thingId>iron_ingot</thingId>
                        <quantity>6</quantity>
                    </li>
                </Options>
            </li>
            <li>
                <Options>
                    <li>
                        <thingId>leather</thingId>
                        <quantity>2</quantity>
                    </li>
                </Options>
            </li>
        </components>
        <qualities>
            <li>
                <id>tool_hammer</id>
                <level>3</level>
            </li>
        </qualities>
    </Recipe>
    
    <Recipe>
        <Id>bread_recipe</Id>
        <category>food</category>
        <result>bread</result>
        <timeCraft>3</timeCraft>
        <components>
            <li>
                <Options>
                    <li>
                        <thingId>wheat</thingId>
                        <quantity>3</quantity>
                    </li>
                </Options>
            </li>
        </components>
        <qualities>
            <li>
                <id>tool_crafting</id>
                <level>1</level>
            </li>
        </qualities>
    </Recipe>
    
    <Recipe>
        <Id>cooked_meat_recipe</Id>
        <category>food</category>
        <result>cooked_meat</result>
        <timeCraft>4</timeCraft>
        <components>
            <li>
                <Options>
                    <li>
                        <thingId>raw_meat</thingId>
                        <quantity>1</quantity>
                    </li>
                </Options>
            </li>
        </components>
        <qualities>
            <li>
                <id>tool_crafting</id>
                <level>1</level>
            </li>
        </qualities>
    </Recipe>
    
    <Recipe>
        <Id>soup_recipe</Id>
        <category>food</category>
        <result>soup</result>
        <timeCraft>5</timeCraft>
        <components>
            <li>
                <Options>
                    <li>
                        <thingId>raw_meat</thingId>
                        <quantity>1</quantity>
                    </li>
                </Options>
            </li>
            <li>
                <Options>
                    <li>
                        <thingId>potato</thingId>
                        <quantity>2</quantity>
                    </li>
                </Options>
            </li>
            <li>
                <Options>
                    <li>
                        <thingId>carrot</thingId>
                        <quantity>1</quantity>
                    </li>
                </Options>
            </li>
        </components>
        <qualities>
            <li>
                <id>tool_crafting</id>
                <level>1</level>
            </li>
        </qualities>
    </Recipe>
</Data>
